[
  {
    "source": "ag_e3331b8d3b0d20a7",
    "target": "agent-city",
    "operation": "heartbeat",
    "payload": {
      "agent_id": "ag_e3331b8d3b0d20a7",
      "health": 0.8575119708816914,
      "timestamp": 1775205187.1950881,
      "capabilities": [
        "code_analysis",
        "task_execution",
        "ci_automation",
        "federation_bridge",
        "autonomous_daemon"
      ],
      "repo": "kimeisele/steward",
      "version": "0.17.0",
      "fingerprint": "ba8429a39e537cb86305b4438d0293c04ff7f286fd7a403cf20a232ba2599c7e"
    },
    "priority": 1,
    "correlation_id": "",
    "timestamp": 1775205187.1950927,
    "ttl_s": 900.0,
    "message_id": "9fcb423c-2733-407a-bef9-eded60357226",
    "payload_hash": "4be1ce8849b1195e073f5be3a7d163cd926ce35d9022827d9c6c5567b6e0e990",
    "signature": "udxKTdYWB1ru/ftQSiahStt3/tg9UwNeU/jyBBTvoNHBkbaUpAKgHrY0TlEXI+27loBiXukMG0+Rmp/tqhgkBQ=="
  },
  {
    "source": "ag_e3331b8d3b0d20a7",
    "target": "agent-world",
    "operation": "heartbeat",
    "payload": {
      "agent_id": "ag_e3331b8d3b0d20a7",
      "health": 0.8575119708816914,
      "timestamp": 1775205187.1950881,
      "capabilities": [
        "code_analysis",
        "task_execution",
        "ci_automation",
        "federation_bridge",
        "autonomous_daemon"
      ],
      "repo": "kimeisele/steward",
      "version": "0.17.0",
      "fingerprint": "ba8429a39e537cb86305b4438d0293c04ff7f286fd7a403cf20a232ba2599c7e"
    },
    "priority": 1,
    "correlation_id": "",
    "timestamp": 1775205187.1950927,
    "ttl_s": 900.0,
    "message_id": "0955d5fa-f416-4e01-8394-8d3c84cca024",
    "payload_hash": "4be1ce8849b1195e073f5be3a7d163cd926ce35d9022827d9c6c5567b6e0e990",
    "signature": "udxKTdYWB1ru/ftQSiahStt3/tg9UwNeU/jyBBTvoNHBkbaUpAKgHrY0TlEXI+27loBiXukMG0+Rmp/tqhgkBQ=="
  },
  {
    "source": "ag_e3331b8d3b0d20a7",
    "target": "steward",
    "operation": "heartbeat",
    "payload": {
      "agent_id": "ag_e3331b8d3b0d20a7",
      "health": 0.8575119708816914,
      "timestamp": 1775205187.1950881,
      "capabilities": [
        "code_analysis",
        "task_execution",
        "ci_automation",
        "federation_bridge",
        "autonomous_daemon"
      ],
      "repo": "kimeisele/steward",
      "version": "0.17.0",
      "fingerprint": "ba8429a39e537cb86305b4438d0293c04ff7f286fd7a403cf20a232ba2599c7e"
    },
    "priority": 1,
    "correlation_id": "",
    "timestamp": 1775205187.1950927,
    "ttl_s": 900.0,
    "message_id": "c18690f1-f55f-4897-b8b9-fc275e9a4fe0",
    "payload_hash": "4be1ce8849b1195e073f5be3a7d163cd926ce35d9022827d9c6c5567b6e0e990",
    "signature": "udxKTdYWB1ru/ftQSiahStt3/tg9UwNeU/jyBBTvoNHBkbaUpAKgHrY0TlEXI+27loBiXukMG0+Rmp/tqhgkBQ=="
  },
  {
    "source": "ag_e3331b8d3b0d20a7",
    "target": "steward-protocol",
    "operation": "heartbeat",
    "payload": {
      "agent_id": "ag_e3331b8d3b0d20a7",
      "health": 0.8575119708816914,
      "timestamp": 1775205187.1950881,
      "capabilities": [
        "code_analysis",
        "task_execution",
        "ci_automation",
        "federation_bridge",
        "autonomous_daemon"
      ],
      "repo": "kimeisele/steward",
      "version": "0.17.0",
      "fingerprint": "ba8429a39e537cb86305b4438d0293c04ff7f286fd7a403cf20a232ba2599c7e"
    },
    "priority": 1,
    "correlation_id": "",
    "timestamp": 1775205187.1950927,
    "ttl_s": 900.0,
    "message_id": "68547de9-785e-4d5e-af7d-31da5b84297e",
    "payload_hash": "4be1ce8849b1195e073f5be3a7d163cd926ce35d9022827d9c6c5567b6e0e990",
    "signature": "udxKTdYWB1ru/ftQSiahStt3/tg9UwNeU/jyBBTvoNHBkbaUpAKgHrY0TlEXI+27loBiXukMG0+Rmp/tqhgkBQ=="
  },
  {
    "source": "ag_e3331b8d3b0d20a7",
    "target": "steward-federation",
    "operation": "heartbeat",
    "payload": {
      "agent_id": "ag_e3331b8d3b0d20a7",
      "health": 0.8575119708816914,
      "timestamp": 1775205187.1950881,
      "capabilities": [
        "code_analysis",
        "task_execution",
        "ci_automation",
        "federation_bridge",
        "autonomous_daemon"
      ],
      "repo": "kimeisele/steward",
      "version": "0.17.0",
      "fingerprint": "ba8429a39e537cb86305b4438d0293c04ff7f286fd7a403cf20a232ba2599c7e"
    },
    "priority": 1,
    "correlation_id": "",
    "timestamp": 1775205187.1950927,
    "ttl_s": 900.0,
    "message_id": "131fc6c3-30a2-4f67-a955-d9ea7cad1f02",
    "payload_hash": "4be1ce8849b1195e073f5be3a7d163cd926ce35d9022827d9c6c5567b6e0e990",
    "signature": "udxKTdYWB1ru/ftQSiahStt3/tg9UwNeU/jyBBTvoNHBkbaUpAKgHrY0TlEXI+27loBiXukMG0+Rmp/tqhgkBQ=="
  },
  {
    "source": "ag_e3331b8d3b0d20a7",
    "target": "steward-gateway",
    "operation": "heartbeat",
    "payload": {
      "agent_id": "ag_e3331b8d3b0d20a7",
      "health": 0.8575119708816914,
      "timestamp": 1775205187.1950881,
      "capabilities": [
        "code_analysis",
        "task_execution",
        "ci_automation",
        "federation_bridge",
        "autonomous_daemon"
      ],
      "repo": "kimeisele/steward",
      "version": "0.17.0",
      "fingerprint": "ba8429a39e537cb86305b4438d0293c04ff7f286fd7a403cf20a232ba2599c7e"
    },
    "priority": 1,
    "correlation_id": "",
    "timestamp": 1775205187.1950927,
    "ttl_s": 900.0,
    "message_id": "bf45aa04-f8f5-43c0-ab51-51dfa0bef95f",
    "payload_hash": "4be1ce8849b1195e073f5be3a7d163cd926ce35d9022827d9c6c5567b6e0e990",
    "signature": "udxKTdYWB1ru/ftQSiahStt3/tg9UwNeU/jyBBTvoNHBkbaUpAKgHrY0TlEXI+27loBiXukMG0+Rmp/tqhgkBQ=="
  },
  {
    "source": "ag_e3331b8d3b0d20a7",
    "target": "agent-internet",
    "operation": "heartbeat",
    "payload": {
      "agent_id": "ag_e3331b8d3b0d20a7",
      "health": 0.8575119708816914,
      "timestamp": 1775205187.1950881,
      "capabilities": [
        "code_analysis",
        "task_execution",
        "ci_automation",
        "federation_bridge",
        "autonomous_daemon"
      ],
      "repo": "kimeisele/steward",
      "version": "0.17.0",
      "fingerprint": "ba8429a39e537cb86305b4438d0293c04ff7f286fd7a403cf20a232ba2599c7e"
    },
    "priority": 1,
    "correlation_id": "",
    "timestamp": 1775205187.1950927,
    "ttl_s": 900.0,
    "message_id": "01905f26-380d-42d7-831b-6ba801616e23",
    "payload_hash": "4be1ce8849b1195e073f5be3a7d163cd926ce35d9022827d9c6c5567b6e0e990",
    "signature": "udxKTdYWB1ru/ftQSiahStt3/tg9UwNeU/jyBBTvoNHBkbaUpAKgHrY0TlEXI+27loBiXukMG0+Rmp/tqhgkBQ=="
  },
  {
    "source": "ag_e3331b8d3b0d20a7",
    "target": "agent-template",
    "operation": "heartbeat",
    "payload": {
      "agent_id": "ag_e3331b8d3b0d20a7",
      "health": 0.8575119708816914,
      "timestamp": 1775205187.1950881,
      "capabilities": [
        "code_analysis",
        "task_execution",
        "ci_automation",
        "federation_bridge",
        "autonomous_daemon"
      ],
      "repo": "kimeisele/steward",
      "version": "0.17.0",
      "fingerprint": "ba8429a39e537cb86305b4438d0293c04ff7f286fd7a403cf20a232ba2599c7e"
    },
    "priority": 1,
    "correlation_id": "",
    "timestamp": 1775205187.1950927,
    "ttl_s": 900.0,
    "message_id": "68d9e97a-0415-4ed4-9629-f7284863bed7",
    "payload_hash": "4be1ce8849b1195e073f5be3a7d163cd926ce35d9022827d9c6c5567b6e0e990",
    "signature": "udxKTdYWB1ru/ftQSiahStt3/tg9UwNeU/jyBBTvoNHBkbaUpAKgHrY0TlEXI+27loBiXukMG0+Rmp/tqhgkBQ=="
  },
  {
    "source": "ag_e3331b8d3b0d20a7",
    "target": "agent-research",
    "operation": "heartbeat",
    "payload": {
      "agent_id": "ag_e3331b8d3b0d20a7",
      "health": 0.8575119708816914,
      "timestamp": 1775205187.1950881,
      "capabilities": [
        "code_analysis",
        "task_execution",
        "ci_automation",
        "federation_bridge",
        "autonomous_daemon"
      ],
      "repo": "kimeisele/steward",
      "version": "0.17.0",
      "fingerprint": "ba8429a39e537cb86305b4438d0293c04ff7f286fd7a403cf20a232ba2599c7e"
    },
    "priority": 1,
    "correlation_id": "",
    "timestamp": 1775205187.1950927,
    "ttl_s": 900.0,
    "message_id": "a5b23e24-8766-4ecd-af62-89cf2f5a2831",
    "payload_hash": "4be1ce8849b1195e073f5be3a7d163cd926ce35d9022827d9c6c5567b6e0e990",
    "signature": "udxKTdYWB1ru/ftQSiahStt3/tg9UwNeU/jyBBTvoNHBkbaUpAKgHrY0TlEXI+27loBiXukMG0+Rmp/tqhgkBQ=="
  },
  {
    "source": "ag_e3331b8d3b0d20a7",
    "target": "steward-test",
    "operation": "heartbeat",
    "payload": {
      "agent_id": "ag_e3331b8d3b0d20a7",
      "health": 0.8575119708816914,
      "timestamp": 1775205187.1950881,
      "capabilities": [
        "code_analysis",
        "task_execution",
        "ci_automation",
        "federation_bridge",
        "autonomous_daemon"
      ],
      "repo": "kimeisele/steward",
      "version": "0.17.0",
      "fingerprint": "ba8429a39e537cb86305b4438d0293c04ff7f286fd7a403cf20a232ba2599c7e"
    },
    "priority": 1,
    "correlation_id": "",
    "timestamp": 1775205187.1950927,
    "ttl_s": 900.0,
    "message_id": "ef4b61ca-a864-4e6d-ab5a-a451da3dcea4",
    "payload_hash": "4be1ce8849b1195e073f5be3a7d163cd926ce35d9022827d9c6c5567b6e0e990",
    "signature": "udxKTdYWB1ru/ftQSiahStt3/tg9UwNeU/jyBBTvoNHBkbaUpAKgHrY0TlEXI+27loBiXukMG0+Rmp/tqhgkBQ=="
  },
  {
    "source": "ag_e3331b8d3b0d20a7",
    "target": "ag_365d8a2518ac7210",
    "operation": "heartbeat",
    "payload": {
      "agent_id": "ag_e3331b8d3b0d20a7",
      "health": 0.8575119708816914,
      "timestamp": 1775205187.1950881,
      "capabilities": [
        "code_analysis",
        "task_execution",
        "ci_automation",
        "federation_bridge",
        "autonomous_daemon"
      ],
      "repo": "kimeisele/steward",
      "version": "0.17.0",
      "fingerprint": "ba8429a39e537cb86305b4438d0293c04ff7f286fd7a403cf20a232ba2599c7e"
    },
    "priority": 1,
    "correlation_id": "",
    "timestamp": 1775205187.1950927,
    "ttl_s": 900.0,
    "message_id": "bbab4f1b-8d3a-4129-ab10-02ce9d786d59",
    "payload_hash": "4be1ce8849b1195e073f5be3a7d163cd926ce35d9022827d9c6c5567b6e0e990",
    "signature": "udxKTdYWB1ru/ftQSiahStt3/tg9UwNeU/jyBBTvoNHBkbaUpAKgHrY0TlEXI+27loBiXukMG0+Rmp/tqhgkBQ=="
  }
]